eventiq/__about__.py
eventiq/__init__.py
eventiq/__main__.py
eventiq/asyncapi.py
eventiq/broker.py
eventiq/cli.py
eventiq/consumer.py
eventiq/decoder.py
eventiq/dependencies.py
eventiq/encoder.py
eventiq/exceptions.py
eventiq/imports.py
eventiq/logging.py
eventiq/middleware.py
eventiq/models.py
eventiq/py.typed
eventiq/results.py
eventiq/service.py
eventiq/settings.py
eventiq/types.py
eventiq/utils.py
eventiq/backends/__init__.py
eventiq/backends/kafka.py
eventiq/backends/nats.py
eventiq/backends/rabbitmq.py
eventiq/backends/redis.py
eventiq/backends/stub.py
eventiq/middlewares/__init__.py
eventiq/middlewares/dlx.py
eventiq/middlewares/error.py
eventiq/middlewares/healthcheck.py
eventiq/middlewares/perf_counter.py
eventiq/middlewares/rate_limits.py
eventiq/middlewares/retries.py
eventiq-1.1.11.dist-info/METADATA
eventiq-1.1.11.dist-info/WHEEL
eventiq-1.1.11.dist-info/entry_points.txt
eventiq-1.1.11.dist-info/licenses/LICENSE
eventiq-1.1.11.dist-info/RECORD
