Metadata-Version: 2.4
Name: eventiq
Version: 1.1.11
Summary: Publish/Subscribe asyncio framework for Python
Project-URL: Documentation, https://github.com/asynq-io/eventiq#readme
Project-URL: Issues, https://github.com/asynq-io/eventiq/issues
Project-URL: Source, https://github.com/asynq-io/eventiq
Author-email: RaRhAeu <rarha_eu@protonmail.com>
License-Expression: Apache-2.0
License-File: LICENSE
Keywords: asyncapi,asyncio,cloud-events,event-driven,framework,microservice,python
Classifier: Development Status :: 4 - Beta
Classifier: Framework :: AsyncIO
Classifier: Intended Audience :: Developers
Classifier: License :: OSI Approved :: Apache Software License
Classifier: Natural Language :: English
Classifier: Operating System :: OS Independent
Classifier: Programming Language :: Python :: 3
Classifier: Programming Language :: Python :: 3.9
Classifier: Programming Language :: Python :: 3.10
Classifier: Programming Language :: Python :: 3.11
Classifier: Programming Language :: Python :: 3.12
Classifier: Topic :: Software Development :: Libraries
Requires-Python: >=3.9
Requires-Dist: anyio<5.0,>4.0
Requires-Dist: pydantic-asyncapi==0.2.1
Requires-Dist: pydantic-settings<3,>2.0
Requires-Dist: pydantic<3,>2.0
Requires-Dist: typer<1.0
Provides-Extra: kafka
Requires-Dist: aiokafka; extra == 'kafka'
Provides-Extra: nats
Requires-Dist: nats-py; extra == 'nats'
Provides-Extra: rabbitmq
Requires-Dist: aio-pika; extra == 'rabbitmq'
Provides-Extra: redis
Requires-Dist: redis; extra == 'redis'
